TinyMCE_on_Pyqt/__init__.py
TinyMCE_on_Pyqt/example.py
TinyMCE_on_Pyqt/main.html
TinyMCE_on_Pyqt/tinymce/CHANGELOG.md
TinyMCE_on_Pyqt/tinymce/zh_CN.js
TinyMCE_on_Pyqt/tinymce/js/tinymce/license.txt
TinyMCE_on_Pyqt/tinymce/js/tinymce/tinymce.d.ts
TinyMCE_on_Pyqt/tinymce/js/tinymce/tinymce.min.js
TinyMCE_on_Pyqt/tinymce/js/tinymce/icons/default/icons.min.js
TinyMCE_on_Pyqt/tinymce/js/tinymce/langs/README.md
TinyMCE_on_Pyqt/tinymce/js/tinymce/models/dom/model.min.js
TinyMCE_on_Pyqt/tinymce/js/tinymce/plugins/advlist/plugin.min.js
TinyMCE_on_Pyqt/tinymce/js/tinymce/plugins/anchor/plugin.min.js
TinyMCE_on_Pyqt/tinymce/js/tinymce/plugins/autolink/plugin.min.js
TinyMCE_on_Pyqt/tinymce/js/tinymce/plugins/autoresize/plugin.min.js
TinyMCE_on_Pyqt/tinymce/js/tinymce/plugins/autosave/plugin.min.js
TinyMCE_on_Pyqt/tinymce/js/tinymce/plugins/charmap/plugin.min.js
TinyMCE_on_Pyqt/tinymce/js/tinymce/plugins/code/plugin.min.js
TinyMCE_on_Pyqt/tinymce/js/tinymce/plugins/codesample/plugin.min.js
TinyMCE_on_Pyqt/tinymce/js/tinymce/plugins/directionality/plugin.min.js
TinyMCE_on_Pyqt/tinymce/js/tinymce/plugins/emoticons/plugin.min.js
TinyMCE_on_Pyqt/tinymce/js/tinymce/plugins/emoticons/js/emojiimages.js
TinyMCE_on_Pyqt/tinymce/js/tinymce/plugins/emoticons/js/emojiimages.min.js
TinyMCE_on_Pyqt/tinymce/js/tinymce/plugins/emoticons/js/emojis.js
TinyMCE_on_Pyqt/tinymce/js/tinymce/plugins/emoticons/js/emojis.min.js
TinyMCE_on_Pyqt/tinymce/js/tinymce/plugins/fullscreen/plugin.min.js
TinyMCE_on_Pyqt/tinymce/js/tinymce/plugins/help/plugin.min.js
TinyMCE_on_Pyqt/tinymce/js/tinymce/plugins/image/plugin.min.js
TinyMCE_on_Pyqt/tinymce/js/tinymce/plugins/importcss/plugin.min.js
TinyMCE_on_Pyqt/tinymce/js/tinymce/plugins/insertdatetime/plugin.min.js
TinyMCE_on_Pyqt/tinymce/js/tinymce/plugins/link/plugin.min.js
TinyMCE_on_Pyqt/tinymce/js/tinymce/plugins/lists/plugin.min.js
TinyMCE_on_Pyqt/tinymce/js/tinymce/plugins/media/plugin.min.js
TinyMCE_on_pyqt-0.1.12.dist-info/METADATA
TinyMCE_on_pyqt-0.1.12.dist-info/WHEEL
TinyMCE_on_pyqt-0.1.12.dist-info/top_level.txt
TinyMCE_on_pyqt-0.1.12.dist-info/RECORD
