Metadata-Version: 2.1
Name: TinyMCE-on-pyqt
Version: 0.1.12
Summary: 在pyqt中方便的使用TinyMCE
Home-page: https://github.com/ovo-Tim/TinyMCE-on-pyqt
Author: TimTu
Author-email: ovo-tim@qq.com
License: GPL License
Classifier: Programming Language :: Python :: 3
Classifier: Operating System :: OS Independent
Requires-Dist: PySide6
